monty_proto/__init__.py
monty_proto/log_anomaly_payload_pb.py
monty_proto-0.6.1.0.dist-info/METADATA
monty_proto-0.6.1.0.dist-info/WHEEL
monty_proto-0.6.1.0.dist-info/top_level.txt
monty_proto-0.6.1.0.dist-info/RECORD
