Metadata-Version: 2.4
Name: monty_proto
Version: 0.6.1.0
Requires-Dist: betterproto~=1.2.0
Dynamic: requires-dist
